MANIFEST.in
README.md
README.rst
setup.py
pyqt2waybinding/__init__.py
pyqt2waybinding.egg-info/PKG-INFO
pyqt2waybinding.egg-info/SOURCES.txt
pyqt2waybinding.egg-info/dependency_links.txt
pyqt2waybinding.egg-info/not-zip-safe
pyqt2waybinding.egg-info/top_level.txt