Metadata-Version: 1.0
Name: pyqt2waybinding
Version: 0.2
Summary: Simple framework for easy 2-way binding with PyQt
Home-page: http://github.com/jkokorian/pyqt2waybinding
Author: J. Kokorian
Author-email: J.Kokorian@TUDelft.nl
License: MIT
Platform: UNKNOWN
